README.rst
setup.py
iamport/__init__.py
iamport/client.py
iamport/decorator.py
iamport_rest_client2.egg-info/PKG-INFO
iamport_rest_client2.egg-info/SOURCES.txt
iamport_rest_client2.egg-info/dependency_links.txt
iamport_rest_client2.egg-info/requires.txt
iamport_rest_client2.egg-info/top_level.txt
tests/__init__.py
tests/conftest.py
tests/test_cancel.py
tests/test_customer_create.py
tests/test_customer_delete.py
tests/test_customer_get.py
tests/test_find.py
tests/test_is_paid.py
tests/test_pay_again.py
tests/test_pay_foreign.py
tests/test_pay_onetime.py
tests/test_pay_schedule.py
tests/test_pay_unschedule.py
tests/test_prepare.py