Metadata-Version: 1.1
Name: iamport-rest-client2
Version: 0.0.2
Summary: REST client for I'mport;(http://www.iamport.kr)
Home-page: https://github.com/james-song/iamport-rest-client-python3
Author: RakGyu Song
Author-email: reeoss@gmail.com
License: MIT License
Platform: UNKNOWN
Classifier: Environment :: Web Environment
Classifier: Intended Audience :: Developers
Classifier: License :: OSI Approved :: MIT License
Classifier: Operating System :: OS Independent
Classifier: Programming Language :: Python
Classifier: Programming Language :: Python :: 3
Classifier: Programming Language :: Python :: 3.4
Classifier: Programming Language :: Python :: 3.5
Classifier: Programming Language :: Python :: 3.6
Classifier: Topic :: Software Development :: Libraries :: Python Modules
